helper/AppAgent.py
helper/AppiumController.py
helper/BaseActions.py
helper/DatabaseManager.py
helper/ParallelRunner.py
helper/TestRailApi.py
helper/Utils.py
helper/XmlElement.py
helper/__init__.py
helper/setup.py
helper/worker.py
qa_helper-0.3.1.dist-info/LICENSE
qa_helper-0.3.1.dist-info/METADATA
qa_helper-0.3.1.dist-info/WHEEL
qa_helper-0.3.1.dist-info/top_level.txt
qa_helper-0.3.1.dist-info/RECORD
