Metadata-Version: 2.1
Name: qa-helper
Version: 0.3.1
Summary: Tools for write automation test easily
Home-page: UNKNOWN
Author: yz
Author-email: mohammad.you92@gmail.com
License: UNKNOWN
Platform: UNKNOWN
Classifier: Programming Language :: Python :: 3
Classifier: License :: OSI Approved :: MIT License
Classifier: Operating System :: OS Independent
